dry_apy_connector/ApiConnector.py
dry_apy_connector/ApiEndpoint.py
dry_apy_connector/DryApiException.py
dry_apy_connector/Loggers.py
dry_apy_connector/ValidationErrorHandler.py
dry_apy_connector-1.0.3.dist-info/METADATA
dry_apy_connector-1.0.3.dist-info/WHEEL
dry_apy_connector-1.0.3.dist-info/RECORD
