Metadata-Version: 2.4
Name: dry-apy-connector
Version: 1.0.3
Summary: Python library for connecting to dry-api
Author-email: Vítek Dvořák <vitek.dvorak@navigo3.com>
Classifier: License :: OSI Approved :: MIT License
Classifier: Operating System :: OS Independent
Classifier: Programming Language :: Python :: 3
Requires-Python: >=3.10
Requires-Dist: requests
